snowcomp/__init__.py
snowcomp/__main__.py
snowcomp-2.0.dist-info/LICENSE
snowcomp-2.0.dist-info/METADATA
snowcomp-2.0.dist-info/WHEEL
snowcomp-2.0.dist-info/entry_points.txt
snowcomp-2.0.dist-info/top_level.txt
snowcomp-2.0.dist-info/RECORD
