Metadata-Version: 2.1
Name: snowcomp
Version: 2.0
Summary: Compares files from different branches and spits out deleted files
Home-page: https://github.com/Kaushal28/SNOW-File-Comparator.git
Author: kaushal28
Author-email: shah.kaushal95@gmail.com
License: UNKNOWN
Platform: UNKNOWN
Classifier: Programming Language :: Python :: 3
Classifier: License :: OSI Approved :: MIT License
Requires-Dist: GitPython (==2.1.11)
